thrml_th/__init__.py
thrml_th/config.py
thrml_th/interop.py
thrml_th/keys.py
thrml_th/sampler.py
thrml_th-0.1.1.dist-info/licenses/LICENSE
thrml_th-0.1.1.dist-info/METADATA
thrml_th-0.1.1.dist-info/WHEEL
thrml_th-0.1.1.dist-info/top_level.txt
thrml_th-0.1.1.dist-info/RECORD
