Metadata-Version: 2.4
Name: thrml-th
Version: 0.1.1
Summary: PyTorch + THRML interop shim (thrml-th).
Author: Lucas Nestler
License: 
Project-URL: Homepage, https://github.com/ClashLuke/thrml_th
Project-URL: Source, https://github.com/ClashLuke/thrml_th
Project-URL: Documentation, https://github.com/ClashLuke/thrml_th/README.md
Keywords: thrml,torch,jax,pgm,interop
Classifier: Development Status :: 3 - Alpha
Classifier: Intended Audience :: Developers
Classifier: Intended Audience :: Science/Research
Classifier: Programming Language :: Python :: 3
Classifier: Programming Language :: Python :: 3.11
Classifier: Programming Language :: Python :: 3.12
Classifier: Topic :: Scientific/Engineering :: Artificial Intelligence
Classifier: Topic :: Software Development :: Libraries
Requires-Python: >=3.11
License-File: LICENSE
Requires-Dist: thrml>=0.1.0
Requires-Dist: torch>=2.4
Requires-Dist: jax>=0.4.30
Requires-Dist: jaxlib>=0.4.30
Requires-Dist: equinox>=0.11.4
Requires-Dist: jaxtyping>=0.2.31
Requires-Dist: torchax>=0.0.9
Provides-Extra: dev
Requires-Dist: pytest>=8.0; extra == "dev"
Requires-Dist: pytest-xdist>=3.5; extra == "dev"
Requires-Dist: rich>=13.7; extra == "dev"
Requires-Dist: ruff>=0.6; extra == "dev"
Requires-Dist: pre-commit>=3.7; extra == "dev"
Provides-Extra: torchax
Requires-Dist: torchax>=0.0.10; extra == "torchax"
Dynamic: license-file
